pyddb/__ddb__.py
pyddb/__init__.py
pyddb/_crash.py
pyddb/_equipment.py
pyddb/_installation.py
pyddb/_instruments.py
pyddb/_perf.py
pyddb/_uniform.py
pyddb/_usbmux.py
pyddb/_utils.py
pyddb/_version.py
pyddb-0.1.16.dist-info/LICENSE
pyddb-0.1.16.dist-info/METADATA
pyddb-0.1.16.dist-info/WHEEL
pyddb-0.1.16.dist-info/entry_points.txt
pyddb-0.1.16.dist-info/top_level.txt
pyddb-0.1.16.dist-info/zip-safe
pyddb-0.1.16.dist-info/RECORD
