Metadata-Version: 2.1
Name: pyddb
Version: 0.1.16
Summary: merge adb and tidevice
Home-page: https://github.com/ruomubingfeng/pyddb
Author: ruomubingfeng
Author-email: ruomubingfeng <ruomubingfeng@163.com>
Maintainer: ruomubingfeng
Maintainer-email: ruomubingfeng <ruomubingfeng@163.com>
License: MIT
Platform: UNKNOWN
Requires-Python: >=3.8
Requires-Dist: tidevice (>=0.6.6)
